perfect_jsonschema/__init__.py
perfect_jsonschema/perfect_jsonschema.py
perfect_jsonschema-2019.2.6.dist-info/LICENSE.md
perfect_jsonschema-2019.2.6.dist-info/METADATA
perfect_jsonschema-2019.2.6.dist-info/WHEEL
perfect_jsonschema-2019.2.6.dist-info/top_level.txt
perfect_jsonschema-2019.2.6.dist-info/zip-safe
perfect_jsonschema-2019.2.6.dist-info/RECORD
