Metadata-Version: 2.1
Name: perfect-jsonschema
Version: 2019.2.6
Summary: Strictly checks that a json schema is valid
Home-page: https://github.com/manycoding/perfect-jsonschema
Maintainer: manycoding
Maintainer-email: manycoding@users.noreply.github.com
License: MIT
Platform: UNKNOWN
Classifier: Development Status :: 4 - Beta
Classifier: Intended Audience :: Developers
Classifier: Operating System :: OS Independent
Classifier: Programming Language :: Python :: 3.6
Classifier: Programming Language :: Python :: 3.7
Requires-Dist: jsonschema[format] (>=3.0.0b3)
